zenduty/__init__.py
zenduty/api_client.py
zenduty/configuration.py
zenduty/exceptions.py
zenduty/rest.py
zenduty/api/__init__.py
zenduty/api/escalationpolicies_api.py
zenduty/api/events_api.py
zenduty/api/incidents_api.py
zenduty/api/integrations_api.py
zenduty/api/members_api.py
zenduty/api/schedules_api.py
zenduty/api/services_api.py
zenduty/api/teams_api.py
zenduty/apiV2/__init__.py
zenduty/apiV2/_logging.py
zenduty/apiV2/client.py
zenduty/apiV2/serializer.py
zenduty/apiV2/accounts/__init__.py
zenduty/apiV2/accounts/members/__init__.py
zenduty/apiV2/accounts/members/models.py
zenduty/apiV2/accounts/roles/__init__.py
zenduty/apiV2/accounts/roles/models.py
zenduty/apiV2/authentication/__init__.py
zenduty/apiV2/authentication/zenduty_credential.py
zenduty/apiV2/events/__init__.py
zenduty/apiV2/events/models.py
zenduty/apiV2/events/router/__init__.py
zenduty/apiV2/events/router/models.py
zenduty/apiV2/incidents/__init__.py
zenduty/apiV2/incidents/models.py
zenduty/apiV2/incidents/notes/__init__.py
zenduty/apiV2/incidents/notes/models.py
zenduty/apiV2/incidents/tags/__init__.py
zenduty/apiV2/incidents/tags/models.py
zenduty/apiV2/teams/__init__.py
zenduty/apiV2/teams/_models.py
zenduty/apiV2/teams/escalation_policies/__init__.py
zenduty/apiV2/teams/escalation_policies/models.py
zenduty/apiV2/teams/escalation_policies/rules.py
zenduty/apiV2/teams/escalation_policies/targets.py
zenduty/apiV2/teams/maintenance/__init__.py
zenduty/apiV2/teams/maintenance/models.py
zenduty/apiV2/teams/oncall/__init__.py
zenduty/apiV2/teams/oncall/models.py
zenduty/apiV2/teams/postmortem/__init__.py
zenduty/apiV2/teams/postmortem/models.py
zenduty/apiV2/teams/priorities/__init__.py
zenduty/apiV2/teams/priorities/models.py
zenduty/apiV2/teams/roles/__init__.py
zenduty/apiV2/teams/roles/models.py
zenduty/apiV2/teams/schedules/__init__.py
zenduty/apiV2/teams/schedules/layers.py
zenduty/apiV2/teams/schedules/models.py
zenduty/apiV2/teams/schedules/overrides.py
zenduty_api-2.6.dist-info/LICENSE
zenduty_api-2.6.dist-info/METADATA
zenduty_api-2.6.dist-info/WHEEL
zenduty_api-2.6.dist-info/top_level.txt
zenduty_api-2.6.dist-info/RECORD
